<annotation>
	<folder>Union4K</folder>
	<filename>00036.jpg</filename>
	<path>/home/yifan/Documents/Union4K/00036.jpg</path>
	<source>
		<database>Unknown</database>
	</source>
	<size>
		<width>3840</width>
		<height>2160</height>
		<depth>3</depth>
	</size>
	<segmented>0</segmented>
	<object>
		<name>16</name>
		<pose>Unspecified</pose>
		<truncated>0</truncated>
		<jaywalking>0</jaywalking>
		<bndbox>
			<xmin>1015</xmin>
			<ymin>769</ymin>
			<xmax>1069</xmax>
			<ymax>915</ymax>
		</bndbox>
	</object>
	<object>
		<name>23</name>
		<pose>Unspecified</pose>
		<truncated>0</truncated>
		<jaywalking>0</jaywalking>
		<bndbox>
			<xmin>2685</xmin>
			<ymin>594</ymin>
			<xmax>2726</xmax>
			<ymax>744</ymax>
		</bndbox>
	</object>
	<object>
		<name>24</name>
		<pose>Unspecified</pose>
		<truncated>0</truncated>
		<jaywalking>0</jaywalking>
		<bndbox>
			<xmin>2660</xmin>
			<ymin>601</ymin>
			<xmax>2697</xmax>
			<ymax>728</ymax>
		</bndbox>
	</object>
	<object>
		<name>25</name>
		<pose>Unspecified</pose>
		<truncated>0</truncated>
		<jaywalking>0</jaywalking>
		<bndbox>
			<xmin>2745</xmin>
			<ymin>545</ymin>
			<xmax>2792</xmax>
			<ymax>655</ymax>
		</bndbox>
	</object>
	<object>
		<name>26</name>
		<pose>Unspecified</pose>
		<truncated>0</truncated>
		<jaywalking>0</jaywalking>
		<bndbox>
			<xmin>1150</xmin>
			<ymin>735</ymin>
			<xmax>1209</xmax>
			<ymax>848</ymax>
		</bndbox>
	</object>
	<object>
		<name>27</name>
		<pose>Unspecified</pose>
		<truncated>0</truncated>
		<jaywalking>0</jaywalking>
		<bndbox>
			<xmin>1083</xmin>
			<ymin>744</ymin>
			<xmax>1153</xmax>
			<ymax>877</ymax>
		</bndbox>
	</object>
	<object>
		<name>28</name>
		<pose>Unspecified</pose>
		<truncated>0</truncated>
		<jaywalking>0</jaywalking>
		<bndbox>
			<xmin>2745</xmin>
			<ymin>563</ymin>
			<xmax>2786</xmax>
			<ymax>715</ymax>
		</bndbox>
	</object>
	<object>
		<name>29</name>
		<pose>Unspecified</pose>
		<truncated>0</truncated>
		<jaywalking>0</jaywalking>
		<bndbox>
			<xmin>2515</xmin>
			<ymin>1577</ymin>
			<xmax>2604</xmax>
			<ymax>1758</ymax>
		</bndbox>
	</object>
	<object>
		<name>30</name>
		<pose>Unspecified</pose>
		<truncated>0</truncated>
		<jaywalking>0</jaywalking>
		<bndbox>
			<xmin>2518</xmin>
			<ymin>1619</ymin>
			<xmax>2615</xmax>
			<ymax>1826</ymax>
		</bndbox>
	</object>
	<object>
		<name>31</name>
		<pose>Unspecified</pose>
		<truncated>0</truncated>
		<jaywalking>0</jaywalking>
		<bndbox>
			<xmin>2190</xmin>
			<ymin>1685</ymin>
			<xmax>2280</xmax>
			<ymax>1890</ymax>
		</bndbox>
	</object>
	<object>
		<name>32</name>
		<pose>Unspecified</pose>
		<truncated>0</truncated>
		<jaywalking>0</jaywalking>
		<bndbox>
			<xmin>1861</xmin>
			<ymin>37</ymin>
			<xmax>1896</xmax>
			<ymax>115</ymax>
		</bndbox>
	</object>
	<object>
		<name>33</name>
		<pose>Unspecified</pose>
		<truncated>0</truncated>
		<jaywalking>0</jaywalking>
		<bndbox>
			<xmin>3249</xmin>
			<ymin>1661</ymin>
			<xmax>3411</xmax>
			<ymax>1899</ymax>
		</bndbox>
	</object>
	<object>
		<name>34</name>
		<pose>Unspecified</pose>
		<truncated>0</truncated>
		<jaywalking>0</jaywalking>
		<bndbox>
			<xmin>185</xmin>
			<ymin>661</ymin>
			<xmax>242</xmax>
			<ymax>763</ymax>
		</bndbox>
	</object>
	<object>
		<name>35</name>
		<pose>Unspecified</pose>
		<truncated>0</truncated>
		<jaywalking>0</jaywalking>
		<bndbox>
			<xmin>3021</xmin>
			<ymin>573</ymin>
			<xmax>3061</xmax>
			<ymax>708</ymax>
		</bndbox>
	</object>
	<object>
		<name>36</name>
		<pose>Unspecified</pose>
		<truncated>0</truncated>
		<jaywalking>0</jaywalking>
		<bndbox>
			<xmin>3050</xmin>
			<ymin>569</ymin>
			<xmax>3107</xmax>
			<ymax>712</ymax>
		</bndbox>
	</object>
	<object>
		<name>37</name>
		<pose>Unspecified</pose>
		<truncated>0</truncated>
		<jaywalking>0</jaywalking>
		<bndbox>
			<xmin>3150</xmin>
			<ymin>561</ymin>
			<xmax>3226</xmax>
			<ymax>704</ymax>
		</bndbox>
	</object>
	<object>
		<name>38</name>
		<pose>Unspecified</pose>
		<truncated>0</truncated>
		<jaywalking>0</jaywalking>
		<bndbox>
			<xmin>3180</xmin>
			<ymin>528</ymin>
			<xmax>3247</xmax>
			<ymax>677</ymax>
		</bndbox>
	</object>
</annotation>
